{
  "version": "5",
  "dialect": "mysql",
  "id": "a55513c1-be04-47b7-ac08-68a372ba592b",
  "prevId": "00000000-0000-0000-0000-000000000000",
  "tables": {
    "Post": {
      "name": "Post",
      "columns": {
        "word": {
          "name": "word",
          "type": "varchar(191)",
          "primaryKey": false,
          "notNull": true,
          "autoincrement": false
        },
        "definition": {
          "name": "definition",
          "type": "varchar(191)",
          "primaryKey": false,
          "notNull": true,
          "autoincrement": false
        },
        "example": {
          "name": "example",
          "type": "varchar(191)",
          "primaryKey": false,
          "notNull": false,
          "autoincrement": false
        },
        "authorName": {
          "name": "authorName",
          "type": "varchar(191)",
          "primaryKey": false,
          "notNull": false,
          "autoincrement": false
        },
        "createdAt": {
          "name": "createdAt",
          "type": "datetime(3)",
          "primaryKey": false,
          "notNull": true,
          "autoincrement": false,
          "default": "(CURRENT_TIMESTAMP(3))"
        },
        "id": {
          "name": "id",
          "type": "int",
          "primaryKey": true,
          "notNull": true,
          "autoincrement": true
        }
      },
      "indexes": {},
      "foreignKeys": {},
      "compositePrimaryKeys": {}
    }
  },
  "schemas": {},
  "_meta": {
    "schemas": {},
    "tables": {},
    "columns": {}
  }
}